really_simple_logger-1.0.0.dist-info/licenses/LICENSE
rs_logger/__init__.py
rs_logger/logger.py
really_simple_logger-1.0.0.dist-info/METADATA
really_simple_logger-1.0.0.dist-info/WHEEL
really_simple_logger-1.0.0.dist-info/top_level.txt
really_simple_logger-1.0.0.dist-info/RECORD
