Metadata-Version: 2.4
Name: really-simple-logger
Version: 1.0.0
Summary: Really simple logging tools
Author-email: Rawser Spicer <rwspicer@alaska.edu>, Tobey Carman <tcarman2@alaska.edu>
Maintainer-email: Rawser Spicer <rwspicer@alaska.edu>
License-Expression: MIT
Project-URL: Homepage, https://github.com/uaf-arctic-eco-modeling/really-simple-logger
Keywords: logger,logging,log
Classifier: Programming Language :: Python :: 3
Classifier: Operating System :: OS Independent
Requires-Python: >=3.8
License-File: LICENSE
Dynamic: license-file
